openfractal_client/__init__.py
openfractal_client/_version.py
openfractal_client/cli.py
openfractal_client-0.1.2.dist-info/LICENSE
openfractal_client-0.1.2.dist-info/METADATA
openfractal_client-0.1.2.dist-info/WHEEL
openfractal_client-0.1.2.dist-info/entry_points.txt
openfractal_client-0.1.2.dist-info/top_level.txt
openfractal_client-0.1.2.dist-info/RECORD
