Metadata-Version: 2.1
Name: openfractal-client
Version: 0.1.2
Summary: A Python client based on QCPortal for Open Drug Discovery (ODD) QM large scale data generation.
Author-email: Hadrien Mary <hadrien@valencediscovery.com>
License: Apache
Project-URL: Source Code, https://github.com/OpenDrugDiscovery/openfractal-client
Project-URL: Bug Tracker, https://github.com/OpenDrugDiscovery/openfractal-client/issues
Project-URL: Documentation, https://github.com/OpenDrugDiscovery/openfractal-client
Classifier: Development Status :: 5 - Production/Stable
Classifier: Intended Audience :: Developers
Classifier: Intended Audience :: Healthcare Industry
Classifier: Intended Audience :: Science/Research
Classifier: Topic :: Scientific/Engineering :: Artificial Intelligence
Classifier: Topic :: Scientific/Engineering :: Bio-Informatics
Classifier: Topic :: Scientific/Engineering :: Information Analysis
Classifier: Topic :: Scientific/Engineering :: Medical Science Apps.
Classifier: Natural Language :: English
Classifier: Operating System :: OS Independent
Classifier: Programming Language :: Python
Classifier: Programming Language :: Python :: 3
Classifier: Programming Language :: Python :: 3.9
Classifier: Programming Language :: Python :: 3.10
Classifier: Programming Language :: Python :: 3.11
Requires-Python: >=3.9
License-File: LICENSE
